CyberRSA/Cipher.py
Cyber_RSA-1.0.0.dist-info/LICENSE
Cyber_RSA-1.0.0.dist-info/METADATA
Cyber_RSA-1.0.0.dist-info/WHEEL
Cyber_RSA-1.0.0.dist-info/entry_points.txt
Cyber_RSA-1.0.0.dist-info/top_level.txt
Cyber_RSA-1.0.0.dist-info/RECORD
