Metadata-Version: 2.1
Name: Cyber-RSA
Version: 1.0.0
Summary: Cipher-RSA
Home-page: https://github.com/IamSantoshKumar/Python
Author: Santhoshkumar
Author-email: shanvsanthosh@gmail.com
License: MIT
Platform: UNKNOWN
Classifier: License :: OSI Approved :: MIT License
Classifier: Programming Language :: Python :: 3
Classifier: Programming Language :: Python :: 3.7
Requires-Dist: Crypto
